{
  "required": true,
  "minVersion": "0.8",
  "package": "net.vukrosic.custommobswordsmod.mixin",
  "compatibilityLevel": "JAVA_17",
  "mixins": [
    "LivingEntityMixin",
    "IronGolemEntityMixin",
    "ItemEntityMixin",
    "EntityMixin",
    "WorldMixin",
    "ServerPlayerInteractionManagerMixin",
    "HungerManagerMixin",
    "FrogBrainMixin",
    "ItemDispenserBehaviourMixin",
    "ServerWorldMixin",
    "PlayerEntityMixin",
    "BedBlockMixin"
  ],
  "client": [
    "ExampleMixin",
    "InGameHudMixin",
    "ClientPlayerInteractionManagerMixin",
    "ClientWorldMixin",
    "HandledScreenMixin",
    "CompassAnglePredicateProviderMixin",
    "SoundManagerMixin",
    "SoundSystemMixin"
  ],
  "injectors": {
    "defaultRequire": 1
  }
}
